Metadata-Version: 1.1
Name: timeseriescv
Version: 0.1
Summary: Scikit-learn style cross-validation classes for time series data
Home-page: UNKNOWN
Author: Samuel Monnier
Author-email: samuel.monnier@gmail.com
License: MIT
Keywords: machine-learning cross-validation scikit-learn time-series
Platform: UNKNOWN
Classifier: Development Status :: 3 - Alpha
Classifier: License :: OSI Approved :: MIT License
Classifier: Programming Language :: Python :: 3.6
Classifier: Topic :: Scientific/Engineering
